{
  "annotations": {
    "list": [
      {
        "$$hashKey": "object:361",
        "builtIn": 1,
        "datasource": "-- Grafana --",
        "enable": true,
        "hide": true,
        "iconColor": "rgba(0, 211, 255, 1)",
        "name": "Annotations & Alerts",
        "type": "dashboard"
      }
    ]
  },
  "description": "Performance metrics for Postgres",
  "editable": true,
  "gnetId": 455,
  "graphTooltip": 1,
  "iteration": 1543924158820,
  "links": [],
  "panels": [
    {
      "aliasColors": {},
      "bars": false,
      "dashLength": 10,
      "dashes": false,
      "datasource": "Prometheus",
      "editable": true,
      "error": false,
      "fill": 1,
      "grid": {},
      "gridPos": {
        "h": 7,
        "w": 18,
        "x": 0,
        "y": 0
      },
      "id": 1,
      "legend": {
        "alignAsTable": true,
        "avg": true,
        "current": false,
        "max": true,
        "min": true,
        "rightSide": true,
        "show": true,
        "total": false,
        "values": true
      },
      "lines": true,
      "linewidth": 1,
      "links": [],
      "nullPointMode": "connected",
      "percentage": false,
      "pointradius": 5,
      "points": false,
      "renderer": "flot",
      "seriesOverrides": [],
      "spaceLength": 10,
      "stack": false,
      "steppedLine": false,
      "targets": [
        {
          "alias": "fetched",
          "dsType": "prometheus",
          "expr": "sum(irate(postgresql_tup_fetched{db=~\"$db\",host=\"$host\"}[5m]))",
          "groupBy": [
            {
              "params": [
                "$interval"
              ],
              "type": "time"
            },
            {
              "params": [
                "null"
              ],
              "type": "fill"
            }
          ],
          "intervalFactor": 2,
          "legendFormat": "fetched",
          "measurement": "postgresql",
          "policy": "default",
          "refId": "A",
          "resultFormat": "time_series",
          "select": [
            [
              {
                "params": [
                  "tup_fetched"
                ],
                "type": "field"
              },
              {
                "params": [],
                "type": "mean"
              },
              {
                "params": [
                  "10s"
                ],
                "type": "non_negative_derivative"
              }
            ]
          ],
          "step": 120,
          "tags": [
            {
              "key": "host",
              "operator": "=~",
              "value": "/^$host$/"
            }
          ]
        },
        {
          "alias": "fetched",
          "dsType": "prometheus",
          "expr": "sum(irate(postgresql_tup_returned{db=~\"$db\",host=\"$host\"}[5m]))",
          "groupBy": [
            {
              "params": [
                "$interval"
              ],
              "type": "time"
            },
            {
              "params": [
                "null"
              ],
              "type": "fill"
            }
          ],
          "intervalFactor": 2,
          "legendFormat": "returned",
          "measurement": "postgresql",
          "policy": "default",
          "refId": "B",
          "resultFormat": "time_series",
          "select": [
            [
              {
                "params": [
                  "tup_fetched"
                ],
                "type": "field"
              },
              {
                "params": [],
                "type": "mean"
              },
              {
                "params": [
                  "10s"
                ],
                "type": "non_negative_derivative"
              }
            ]
          ],
          "step": 120,
          "tags": [
            {
              "key": "host",
              "operator": "=~",
              "value": "/^$host$/"
            }
          ]
        },
        {
          "alias": "fetched",
          "dsType": "prometheus",
          "expr": "sum(irate(postgresql_tup_inserted{db=~\"$db\",host=\"$host\"}[5m]))",
          "groupBy": [
            {
              "params": [
                "$interval"
              ],
              "type": "time"
            },
            {
              "params": [
                "null"
              ],
              "type": "fill"
            }
          ],
          "intervalFactor": 2,
          "legendFormat": "inserted",
          "measurement": "postgresql",
          "policy": "default",
          "refId": "C",
          "resultFormat": "time_series",
          "select": [
            [
              {
                "params": [
                  "tup_fetched"
                ],
                "type": "field"
              },
              {
                "params": [],
                "type": "mean"
              },
              {
                "params": [
                  "10s"
                ],
                "type": "non_negative_derivative"
              }
            ]
          ],
          "step": 120,
          "tags": [
            {
              "key": "host",
              "operator": "=~",
              "value": "/^$host$/"
            }
          ]
        },
        {
          "alias": "fetched",
          "dsType": "prometheus",
          "expr": "sum(irate(postgresql_tup_updated{db=~\"$db\",host=\"$host\"}[5m]))",
          "groupBy": [
            {
              "params": [
                "$interval"
              ],
              "type": "time"
            },
            {
              "params": [
                "null"
              ],
              "type": "fill"
            }
          ],
          "intervalFactor": 2,
          "legendFormat": "updated",
          "measurement": "postgresql",
          "policy": "default",
          "refId": "D",
          "resultFormat": "time_series",
          "select": [
            [
              {
                "params": [
                  "tup_fetched"
                ],
                "type": "field"
              },
              {
                "params": [],
                "type": "mean"
              },
              {
                "params": [
                  "10s"
                ],
                "type": "non_negative_derivative"
              }
            ]
          ],
          "step": 120,
          "tags": [
            {
              "key": "host",
              "operator": "=~",
              "value": "/^$host$/"
            }
          ]
        },
        {
          "alias": "fetched",
          "dsType": "prometheus",
          "expr": "sum(irate(postgresql_tup_deleted{db=~\"$db\",host=\"$host\"}[5m]))",
          "groupBy": [
            {
              "params": [
                "$interval"
              ],
              "type": "time"
            },
            {
              "params": [
                "null"
              ],
              "type": "fill"
            }
          ],
          "intervalFactor": 2,
          "legendFormat": "deleted",
          "measurement": "postgresql",
          "policy": "default",
          "refId": "E",
          "resultFormat": "time_series",
          "select": [
            [
              {
                "params": [
                  "tup_fetched"
                ],
                "type": "field"
              },
              {
                "params": [],
                "type": "mean"
              },
              {
                "params": [
                  "10s"
                ],
                "type": "non_negative_derivative"
              }
            ]
          ],
          "step": 120,
          "tags": [
            {
              "key": "host",
              "operator": "=~",
              "value": "/^$host$/"
            }
          ]
        }
      ],
      "thresholds": [],
      "timeFrom": null,
      "timeShift": null,
      "title": "Rows",
      "tooltip": {
        "msResolution": true,
        "shared": true,
        "sort": 0,
        "value_type": "cumulative"
      },
      "type": "graph",
      "xaxis": {
        "buckets": null,
        "mode": "time",
        "name": null,
        "show": true,
        "values": []
      },
      "yaxes": [
        {
          "$$hashKey": "object:2059",
          "format": "short",
          "label": null,
          "logBase": 10,
          "max": null,
          "min": null,
          "show": true
        },
        {
          "$$hashKey": "object:2060",
          "format": "short",
          "label": null,
          "logBase": 1,
          "max": null,
          "min": null,
          "show": true
        }
      ],
      "yaxis": {
        "align": false,
        "alignLevel": null
      }
    },
    {
      "aliasColors": {},
      "bars": false,
      "dashLength": 10,
      "dashes": false,
      "datasource": null,
      "fill": 1,
      "gridPos": {
        "h": 7,
        "w": 6,
        "x": 18,
        "y": 0
      },
      "id": 18,
      "legend": {
        "avg": false,
        "current": false,
        "max": false,
        "min": false,
        "show": true,
        "total": false,
        "values": false
      },
      "lines": true,
      "linewidth": 1,
      "links": [],
      "nullPointMode": "null",
      "percentage": false,
      "pointradius": 5,
      "points": false,
      "renderer": "flot",
      "seriesOverrides": [],
      "spaceLength": 10,
      "stack": false,
      "steppedLine": false,
      "targets": [
        {
          "$$hashKey": "object:2320",
          "expr": "sum(rate(postgresql_xact_commit{host=\"$host\", db=~\"$db\"}[5m]))",
          "format": "time_series",
          "intervalFactor": 1,
          "legendFormat": "Commits",
          "refId": "A"
        },
        {
          "$$hashKey": "object:2342",
          "expr": "sum(rate(postgresql_xact_rollback{host=\"$host\", db=~\"$db\"}[5m]))",
          "format": "time_series",
          "intervalFactor": 1,
          "legendFormat": "Rollbacks",
          "refId": "B"
        }
      ],
      "thresholds": [],
      "timeFrom": null,
      "timeShift": null,
      "title": "Queries",
      "tooltip": {
        "shared": true,
        "sort": 0,
        "value_type": "individual"
      },
      "type": "graph",
      "xaxis": {
        "buckets": null,
        "mode": "time",
        "name": null,
        "show": true,
        "values": []
      },
      "yaxes": [
        {
          "$$hashKey": "object:2553",
          "format": "ops",
          "label": null,
          "logBase": 1,
          "max": null,
          "min": null,
          "show": true
        },
        {
          "$$hashKey": "object:2554",
          "format": "short",
          "label": null,
          "logBase": 1,
          "max": null,
          "min": null,
          "show": true
        }
      ],
      "yaxis": {
        "align": false,
        "alignLevel": null
      }
    },
    {
      "aliasColors": {},
      "bars": false,
      "dashLength": 10,
      "dashes": false,
      "datasource": "Prometheus",
      "decimals": 1,
      "editable": true,
      "error": false,
      "fill": 1,
      "grid": {},
      "gridPos": {
        "h": 7,
        "w": 18,
        "x": 0,
        "y": 7
      },
      "height": "",
      "id": 2,
      "legend": {
        "alignAsTable": true,
        "avg": true,
        "current": false,
        "hideZero": false,
        "max": true,
        "min": true,
        "rightSide": true,
        "show": true,
        "total": false,
        "values": true
      },
      "lines": true,
      "linewidth": 1,
      "links": [],
      "nullPointMode": "connected",
      "percentage": false,
      "pointradius": 5,
      "points": false,
      "renderer": "flot",
      "seriesOverrides": [],
      "spaceLength": 10,
      "stack": false,
      "steppedLine": false,
      "targets": [
        {
          "$$hashKey": "object:592",
          "alias": "Buffers Allocated",
          "dsType": "prometheus",
          "expr": "rate(postgresql_buffers_alloc{host=\"$host\"}[5m])",
          "format": "time_series",
          "groupBy": [
            {
              "params": [
                "$interval"
              ],
              "type": "time"
            },
            {
              "params": [
                "null"
              ],
              "type": "fill"
            }
          ],
          "intervalFactor": 2,
          "legendFormat": "alloc",
          "measurement": "postgresql",
          "metric": "postgresql_buffers_alloc",
          "policy": "default",
          "refId": "A",
          "resultFormat": "time_series",
          "select": [
            [
              {
                "params": [
                  "buffers_alloc"
                ],
                "type": "field"
              },
              {
                "params": [],
                "type": "mean"
              },
              {
                "params": [],
                "type": "difference"
              }
            ]
          ],
          "step": 120,
          "tags": [
            {
              "key": "host",
              "operator": "=~",
              "value": "/^$host$/"
            }
          ]
        },
        {
          "$$hashKey": "object:593",
          "alias": "Buffers Allocated",
          "dsType": "prometheus",
          "expr": "rate(postgresql_buffers_backend_fsync{host='$host'}[5m])",
          "format": "time_series",
          "groupBy": [
            {
              "params": [
                "$interval"
              ],
              "type": "time"
            },
            {
              "params": [
                "null"
              ],
              "type": "fill"
            }
          ],
          "intervalFactor": 2,
          "legendFormat": "backend_fsync",
          "measurement": "postgresql",
          "metric": "postgresql_buffers_backend_fsync",
          "policy": "default",
          "refId": "B",
          "resultFormat": "time_series",
          "select": [
            [
              {
                "params": [
                  "buffers_alloc"
                ],
                "type": "field"
              },
              {
                "params": [],
                "type": "mean"
              },
              {
                "params": [],
                "type": "difference"
              }
            ]
          ],
          "step": 120,
          "tags": [
            {
              "key": "host",
              "operator": "=~",
              "value": "/^$host$/"
            }
          ]
        },
        {
          "$$hashKey": "object:594",
          "alias": "Buffers Allocated",
          "dsType": "prometheus",
          "expr": "rate(postgresql_buffers_backend{host='$host'}[5m])",
          "format": "time_series",
          "groupBy": [
            {
              "params": [
                "$interval"
              ],
              "type": "time"
            },
            {
              "params": [
                "null"
              ],
              "type": "fill"
            }
          ],
          "intervalFactor": 2,
          "legendFormat": "backend",
          "measurement": "postgresql",
          "metric": "postgresql_buffers_backend",
          "policy": "default",
          "refId": "C",
          "resultFormat": "time_series",
          "select": [
            [
              {
                "params": [
                  "buffers_alloc"
                ],
                "type": "field"
              },
              {
                "params": [],
                "type": "mean"
              },
              {
                "params": [],
                "type": "difference"
              }
            ]
          ],
          "step": 120,
          "tags": [
            {
              "key": "host",
              "operator": "=~",
              "value": "/^$host$/"
            }
          ]
        },
        {
          "$$hashKey": "object:595",
          "alias": "Buffers Allocated",
          "dsType": "prometheus",
          "expr": "rate(postgresql_buffers_clean{host='$host'}[5m])",
          "format": "time_series",
          "groupBy": [
            {
              "params": [
                "$interval"
              ],
              "type": "time"
            },
            {
              "params": [
                "null"
              ],
              "type": "fill"
            }
          ],
          "intervalFactor": 2,
          "legendFormat": "clean",
          "measurement": "postgresql",
          "metric": "postgresql_buffers_clean",
          "policy": "default",
          "refId": "D",
          "resultFormat": "time_series",
          "select": [
            [
              {
                "params": [
                  "buffers_alloc"
                ],
                "type": "field"
              },
              {
                "params": [],
                "type": "mean"
              },
              {
                "params": [],
                "type": "difference"
              }
            ]
          ],
          "step": 120,
          "tags": [
            {
              "key": "host",
              "operator": "=~",
              "value": "/^$host$/"
            }
          ]
        },
        {
          "$$hashKey": "object:596",
          "alias": "Buffers Allocated",
          "dsType": "prometheus",
          "expr": "rate(postgresql_buffers_checkpoint{host='$host'}[5m])",
          "format": "time_series",
          "groupBy": [
            {
              "params": [
                "$interval"
              ],
              "type": "time"
            },
            {
              "params": [
                "null"
              ],
              "type": "fill"
            }
          ],
          "interval": "",
          "intervalFactor": 2,
          "legendFormat": "checkpoint",
          "measurement": "postgresql",
          "metric": "postgresql_buffers_checkpoint",
          "policy": "default",
          "refId": "E",
          "resultFormat": "time_series",
          "select": [
            [
              {
                "params": [
                  "buffers_alloc"
                ],
                "type": "field"
              },
              {
                "params": [],
                "type": "mean"
              },
              {
                "params": [],
                "type": "difference"
              }
            ]
          ],
          "step": 120,
          "tags": [
            {
              "key": "host",
              "operator": "=~",
              "value": "/^$host$/"
            }
          ]
        }
      ],
      "thresholds": [],
      "timeFrom": null,
      "timeShift": null,
      "title": "Buffers",
      "tooltip": {
        "msResolution": false,
        "shared": true,
        "sort": 0,
        "value_type": "cumulative"
      },
      "type": "graph",
      "xaxis": {
        "buckets": null,
        "mode": "time",
        "name": null,
        "show": true,
        "values": []
      },
      "yaxes": [
        {
          "$$hashKey": "object:2007",
          "format": "short",
          "label": null,
          "logBase": 10,
          "max": null,
          "min": 0,
          "show": true
        },
        {
          "$$hashKey": "object:2008",
          "format": "short",
          "label": null,
          "logBase": 1,
          "max": null,
          "min": null,
          "show": true
        }
      ],
      "yaxis": {
        "align": false,
        "alignLevel": null
      }
    },
    {
      "aliasColors": {},
      "bars": false,
      "dashLength": 10,
      "dashes": false,
      "datasource": null,
      "fill": 1,
      "gridPos": {
        "h": 7,
        "w": 6,
        "x": 18,
        "y": 7
      },
      "id": 30,
      "legend": {
        "avg": false,
        "current": true,
        "max": false,
        "min": false,
        "show": true,
        "total": false,
        "values": true
      },
      "lines": true,
      "linewidth": 1,
      "links": [],
      "nullPointMode": "null",
      "percentage": false,
      "pointradius": 5,
      "points": false,
      "renderer": "flot",
      "seriesOverrides": [],
      "spaceLength": 10,
      "stack": false,
      "steppedLine": false,
      "targets": [
        {
          "$$hashKey": "object:4103",
          "expr": "max(postgresql_numbackends{db=~\"$db\",host=\"$host\"})",
          "format": "time_series",
          "intervalFactor": 1,
          "legendFormat": "Connections",
          "refId": "A"
        }
      ],
      "thresholds": [],
      "timeFrom": null,
      "timeShift": null,
      "title": "Connections",
      "tooltip": {
        "shared": true,
        "sort": 0,
        "value_type": "individual"
      },
      "type": "graph",
      "xaxis": {
        "buckets": null,
        "mode": "time",
        "name": null,
        "show": true,
        "values": []
      },
      "yaxes": [
        {
          "$$hashKey": "object:4195",
          "format": "short",
          "label": null,
          "logBase": 1,
          "max": null,
          "min": null,
          "show": true
        },
        {
          "$$hashKey": "object:4196",
          "format": "short",
          "label": null,
          "logBase": 1,
          "max": null,
          "min": null,
          "show": true
        }
      ],
      "yaxis": {
        "align": false,
        "alignLevel": null
      }
    },
    {
      "aliasColors": {},
      "bars": false,
      "dashLength": 10,
      "dashes": false,
      "datasource": null,
      "fill": 1,
      "gridPos": {
        "h": 7,
        "w": 12,
        "x": 0,
        "y": 14
      },
      "id": 15,
      "legend": {
        "avg": false,
        "current": false,
        "max": false,
        "min": false,
        "show": true,
        "total": false,
        "values": false
      },
      "lines": true,
      "linewidth": 1,
      "links": [],
      "nullPointMode": "null",
      "percentage": false,
      "pointradius": 5,
      "points": false,
      "renderer": "flot",
      "seriesOverrides": [
        {
          "$$hashKey": "object:1322",
          "alias": "/^Checkpoint/",
          "lines": false,
          "points": true,
          "yaxis": 2
        }
      ],
      "spaceLength": 10,
      "stack": false,
      "steppedLine": false,
      "targets": [
        {
          "$$hashKey": "object:680",
          "expr": "irate(postgresql_checkpoint_sync_time{host=\"$host\"}[5m])",
          "format": "time_series",
          "hide": false,
          "intervalFactor": 1,
          "legendFormat": "Sync time",
          "refId": "A"
        },
        {
          "$$hashKey": "object:998",
          "expr": "irate(postgresql_checkpoint_write_time{host=\"$host\"}[5m])",
          "format": "time_series",
          "interval": "",
          "intervalFactor": 1,
          "legendFormat": "Write time",
          "refId": "B"
        },
        {
          "$$hashKey": "object:1098",
          "expr": "irate(postgresql_checkpoints_timed{host=\"$host\"}[1m]) > 0",
          "format": "time_series",
          "intervalFactor": 1,
          "legendFormat": "Checkpoint (timed)",
          "refId": "C"
        },
        {
          "$$hashKey": "object:1405",
          "expr": "irate(postgresql_checkpoints_req{host=\"$host\"}[1m]) > 0",
          "format": "time_series",
          "intervalFactor": 1,
          "legendFormat": "Checkpoint (requested)",
          "refId": "D"
        }
      ],
      "thresholds": [],
      "timeFrom": null,
      "timeShift": null,
      "title": "Checkpointing",
      "tooltip": {
        "shared": true,
        "sort": 0,
        "value_type": "individual"
      },
      "type": "graph",
      "xaxis": {
        "buckets": null,
        "mode": "time",
        "name": null,
        "show": true,
        "values": []
      },
      "yaxes": [
        {
          "$$hashKey": "object:1026",
          "format": "dtdurationms",
          "label": null,
          "logBase": 10,
          "max": null,
          "min": null,
          "show": true
        },
        {
          "$$hashKey": "object:1027",
          "format": "short",
          "label": null,
          "logBase": 1,
          "max": null,
          "min": "0",
          "show": true
        }
      ],
      "yaxis": {
        "align": false,
        "alignLevel": null
      }
    },
    {
      "aliasColors": {},
      "bars": false,
      "dashLength": 10,
      "dashes": false,
      "datasource": "Prometheus",
      "editable": true,
      "error": false,
      "fill": 1,
      "grid": {},
      "gridPos": {
        "h": 7,
        "w": 12,
        "x": 12,
        "y": 14
      },
      "id": 3,
      "legend": {
        "avg": false,
        "current": false,
        "max": false,
        "min": false,
        "show": true,
        "total": false,
        "values": false
      },
      "lines": true,
      "linewidth": 2,
      "links": [],
      "nullPointMode": "connected",
      "percentage": false,
      "pointradius": 5,
      "points": false,
      "renderer": "flot",
      "seriesOverrides": [],
      "spaceLength": 10,
      "stack": false,
      "steppedLine": false,
      "targets": [
        {
          "$$hashKey": "object:427",
          "alias": "conflicts",
          "dsType": "prometheus",
          "expr": "sum(increase(postgresql_deadlocks{db=~\"$db\",host=\"$host\"}[5m]))",
          "format": "time_series",
          "groupBy": [
            {
              "params": [
                "$interval"
              ],
              "type": "time"
            },
            {
              "params": [
                "null"
              ],
              "type": "fill"
            }
          ],
          "intervalFactor": 2,
          "legendFormat": "deadlocks",
          "measurement": "postgresql",
          "metric": "postgresql_deadlocks",
          "policy": "default",
          "refId": "A",
          "resultFormat": "time_series",
          "select": [
            [
              {
                "params": [
                  "conflicts"
                ],
                "type": "field"
              },
              {
                "params": [],
                "type": "mean"
              },
              {
                "params": [],
                "type": "difference"
              }
            ]
          ],
          "step": 240,
          "tags": [
            {
              "key": "host",
              "operator": "=~",
              "value": "/^$host$/"
            }
          ]
        },
        {
          "$$hashKey": "object:428",
          "alias": "deadlocks",
          "dsType": "prometheus",
          "expr": "sum(increase(postgresql_conflicts{db=~\"$db\",host=\"$host\"}[5m]))",
          "format": "time_series",
          "groupBy": [
            {
              "params": [
                "$interval"
              ],
              "type": "time"
            },
            {
              "params": [
                "null"
              ],
              "type": "fill"
            }
          ],
          "intervalFactor": 2,
          "legendFormat": "conflicts",
          "measurement": "postgresql",
          "metric": "postgresql_conflicts",
          "policy": "default",
          "refId": "B",
          "resultFormat": "time_series",
          "select": [
            [
              {
                "params": [
                  "deadlocks"
                ],
                "type": "field"
              },
              {
                "params": [],
                "type": "mean"
              },
              {
                "params": [],
                "type": "difference"
              }
            ]
          ],
          "step": 240,
          "tags": [
            {
              "key": "host",
              "operator": "=~",
              "value": "/^$host$/"
            }
          ]
        }
      ],
      "thresholds": [],
      "timeFrom": null,
      "timeShift": null,
      "title": "Conflicts/Deadlocks",
      "tooltip": {
        "msResolution": false,
        "shared": true,
        "sort": 0,
        "value_type": "cumulative"
      },
      "type": "graph",
      "xaxis": {
        "buckets": null,
        "mode": "time",
        "name": null,
        "show": true,
        "values": []
      },
      "yaxes": [
        {
          "format": "short",
          "label": null,
          "logBase": 1,
          "max": null,
          "min": 0,
          "show": true
        },
        {
          "format": "short",
          "label": null,
          "logBase": 1,
          "max": null,
          "min": null,
          "show": true
        }
      ],
      "yaxis": {
        "align": false,
        "alignLevel": null
      }
    },
    {
      "aliasColors": {},
      "bars": false,
      "dashLength": 10,
      "dashes": false,
      "datasource": "Prometheus",
      "editable": true,
      "error": false,
      "fill": 1,
      "grid": {},
      "gridPos": {
        "h": 7,
        "w": 12,
        "x": 0,
        "y": 21
      },
      "id": 12,
      "legend": {
        "avg": false,
        "current": false,
        "max": false,
        "min": false,
        "show": true,
        "total": false,
        "values": false
      },
      "lines": true,
      "linewidth": 2,
      "links": [],
      "nullPointMode": "connected",
      "percentage": true,
      "pointradius": 1,
      "points": false,
      "renderer": "flot",
      "seriesOverrides": [
        {
          "$$hashKey": "object:3372",
          "alias": "Blocks read from disk",
          "yaxis": 2
        }
      ],
      "spaceLength": 10,
      "stack": false,
      "steppedLine": false,
      "targets": [
        {
          "$$hashKey": "object:774",
          "expr": "sum(postgresql_blks_hit{db=~\"$db\",host=\"$host\"}) / (sum(postgresql_blks_hit{db=~\"$db\",host=\"$host\"}) + sum(postgresql_blks_read{db=~\"$db\",host=\"$host\"}))",
          "format": "time_series",
          "intervalFactor": 2,
          "legendFormat": "cache hit rate",
          "metric": "postgresql_blks",
          "refId": "A",
          "step": 240
        },
        {
          "$$hashKey": "object:775",
          "expr": "sum(irate(postgresql_blks_read{db=~\"$db\",host=\"$host\"}[5m]))",
          "format": "time_series",
          "intervalFactor": 2,
          "legendFormat": "Blocks read from disk",
          "metric": "postg",
          "refId": "B"
        }
      ],
      "thresholds": [],
      "timeFrom": null,
      "timeShift": null,
      "title": "Cache hit ratio",
      "tooltip": {
        "msResolution": false,
        "shared": true,
        "sort": 0,
        "value_type": "cumulative"
      },
      "type": "graph",
      "xaxis": {
        "buckets": null,
        "mode": "time",
        "name": null,
        "show": true,
        "values": []
      },
      "yaxes": [
        {
          "$$hashKey": "object:3408",
          "format": "percentunit",
          "label": "",
          "logBase": 1,
          "max": null,
          "min": "0",
          "show": true
        },
        {
          "$$hashKey": "object:3409",
          "format": "short",
          "label": null,
          "logBase": 1,
          "max": null,
          "min": null,
          "show": true
        }
      ],
      "yaxis": {
        "align": false,
        "alignLevel": null
      }
    },
    {
      "aliasColors": {},
      "bars": false,
      "dashLength": 10,
      "dashes": false,
      "datasource": "Prometheus",
      "editable": true,
      "error": false,
      "fill": 1,
      "grid": {},
      "gridPos": {
        "h": 7,
        "w": 6,
        "x": 12,
        "y": 21
      },
      "id": 16,
      "legend": {
        "avg": false,
        "current": false,
        "max": false,
        "min": false,
        "show": true,
        "total": false,
        "values": false
      },
      "lines": true,
      "linewidth": 2,
      "links": [],
      "nullPointMode": "connected",
      "percentage": true,
      "pointradius": 1,
      "points": false,
      "renderer": "flot",
      "seriesOverrides": [],
      "spaceLength": 10,
      "stack": false,
      "steppedLine": false,
      "targets": [
        {
          "$$hashKey": "object:774",
          "expr": "sum(rate(postgresql_temp_bytes{host=\"$host\", db=~\"$db\"}[5m]))",
          "format": "time_series",
          "interval": "",
          "intervalFactor": 2,
          "legendFormat": "Bytes written",
          "metric": "postgresql_blks",
          "refId": "A",
          "step": 240
        },
        {
          "$$hashKey": "object:775",
          "expr": "",
          "format": "time_series",
          "interval": "",
          "intervalFactor": 2,
          "legendFormat": "",
          "metric": "postg",
          "refId": "B"
        }
      ],
      "thresholds": [],
      "timeFrom": null,
      "timeShift": null,
      "title": "Temporary files",
      "tooltip": {
        "msResolution": false,
        "shared": true,
        "sort": 0,
        "value_type": "cumulative"
      },
      "type": "graph",
      "xaxis": {
        "buckets": null,
        "mode": "time",
        "name": null,
        "show": true,
        "values": []
      },
      "yaxes": [
        {
          "$$hashKey": "object:2168",
          "format": "bytes",
          "label": "",
          "logBase": 1,
          "max": null,
          "min": "0",
          "show": true
        },
        {
          "$$hashKey": "object:2169",
          "format": "short",
          "label": null,
          "logBase": 1,
          "max": null,
          "min": null,
          "show": true
        }
      ],
      "yaxis": {
        "align": false,
        "alignLevel": null
      }
    },
    {
      "aliasColors": {},
      "bars": false,
      "dashLength": 10,
      "dashes": false,
      "datasource": "Prometheus",
      "description": "Unclear if this is the right figure.",
      "fill": 1,
      "gridPos": {
        "h": 7,
        "w": 6,
        "x": 18,
        "y": 21
      },
      "id": 22,
      "legend": {
        "avg": true,
        "current": false,
        "max": true,
        "min": false,
        "show": true,
        "total": false,
        "values": true
      },
      "lines": true,
      "linewidth": 1,
      "links": [],
      "nullPointMode": "null",
      "percentage": false,
      "pointradius": 5,
      "points": false,
      "renderer": "flot",
      "seriesOverrides": [
        {
          "alias": "Write",
          "transform": "negative-Y"
        }
      ],
      "spaceLength": 10,
      "stack": false,
      "steppedLine": false,
      "targets": [
        {
          "$$hashKey": "object:3086",
          "expr": "sum(rate(diskio_reads{host=\"$host\", name!~\".*[0-9]$\"}[5m]))",
          "format": "time_series",
          "interval": "",
          "intervalFactor": 2,
          "legendFormat": "Read",
          "metric": "diskio",
          "refId": "A",
          "step": 4
        },
        {
          "$$hashKey": "object:3087",
          "expr": "sum(rate(diskio_writes{host=\"$host\", name!~\".*[0-9]$\"}[5m]))",
          "format": "time_series",
          "interval": "",
          "intervalFactor": 2,
          "legendFormat": "Write",
          "metric": "diskio",
          "refId": "B",
          "step": 4
        }
      ],
      "thresholds": [
        {
          "colorMode": "warning",
          "fill": true,
          "line": true,
          "op": "gt",
          "value": 250
        },
        {
          "colorMode": "warning",
          "fill": true,
          "line": true,
          "op": "lt",
          "value": -250
        }
      ],
      "timeFrom": null,
      "timeShift": null,
      "title": "IOPS",
      "tooltip": {
        "shared": true,
        "sort": 0,
        "value_type": "individual"
      },
      "type": "graph",
      "xaxis": {
        "buckets": null,
        "mode": "time",
        "name": null,
        "show": true,
        "values": []
      },
      "yaxes": [
        {
          "format": "iops",
          "label": null,
          "logBase": 1,
          "max": null,
          "min": null,
          "show": true
        },
        {
          "format": "short",
          "label": null,
          "logBase": 1,
          "max": null,
          "min": null,
          "show": true
        }
      ],
      "yaxis": {
        "align": false,
        "alignLevel": null
      }
    },
    {
      "aliasColors": {},
      "bars": false,
      "dashLength": 10,
      "dashes": false,
      "datasource": "Prometheus",
      "fill": 1,
      "gridPos": {
        "h": 7,
        "w": 6,
        "x": 0,
        "y": 28
      },
      "id": 20,
      "legend": {
        "alignAsTable": false,
        "avg": true,
        "current": false,
        "max": false,
        "min": false,
        "rightSide": false,
        "show": true,
        "total": false,
        "values": true
      },
      "lines": true,
      "linewidth": 1,
      "links": [],
      "nullPointMode": "null",
      "percentage": true,
      "pointradius": 5,
      "points": false,
      "renderer": "flot",
      "seriesOverrides": [
        {
          "alias": "Idle",
          "color": "#447EBC"
        },
        {
          "alias": "IOWait",
          "color": "#58140C"
        },
        {
          "alias": "User",
          "color": "#7EB26D"
        }
      ],
      "spaceLength": 10,
      "stack": true,
      "steppedLine": false,
      "targets": [
        {
          "$$hashKey": "object:2935",
          "expr": "avg(cpu_usage_iowait{cpu=\"cpu-total\", host=\"$host\"})",
          "format": "time_series",
          "hide": false,
          "interval": "",
          "intervalFactor": 2,
          "legendFormat": "IOWait",
          "metric": "cpu_usage",
          "refId": "C",
          "step": 4
        },
        {
          "$$hashKey": "object:2936",
          "expr": "avg(cpu_usage_system{cpu=\"cpu-total\",host=\"$host\"})",
          "format": "time_series",
          "interval": "",
          "intervalFactor": 2,
          "legendFormat": "System",
          "metric": "cpu_usage_nice",
          "refId": "E",
          "step": 4
        },
        {
          "$$hashKey": "object:2937",
          "expr": "avg(cpu_usage_user{cpu=\"cpu-total\", host=\"$host\"})",
          "format": "time_series",
          "hide": false,
          "interval": "",
          "intervalFactor": 2,
          "legendFormat": "User",
          "metric": "cpu_usage_user",
          "refId": "A",
          "step": 4
        },
        {
          "$$hashKey": "object:2938",
          "expr": "avg(cpu_usage_idle{cpu=\"cpu-total\",host=\"$host\"})",
          "format": "time_series",
          "interval": "",
          "intervalFactor": 2,
          "legendFormat": "Idle",
          "metric": "cpu_usage_idle",
          "refId": "B",
          "step": 4
        },
        {
          "$$hashKey": "object:2939",
          "expr": "avg(cpu_usage_steal{cpu=\"cpu-total\",host=\"$host\"})",
          "format": "time_series",
          "intervalFactor": 2,
          "legendFormat": "Steal",
          "metric": "cpu_usage_steal",
          "refId": "D",
          "step": 4
        }
      ],
      "thresholds": [],
      "timeFrom": null,
      "timeShift": null,
      "title": "CPU",
      "tooltip": {
        "shared": true,
        "sort": 0,
        "value_type": "individual"
      },
      "type": "graph",
      "xaxis": {
        "buckets": null,
        "mode": "time",
        "name": null,
        "show": true,
        "values": []
      },
      "yaxes": [
        {
          "format": "percent",
          "label": null,
          "logBase": 1,
          "max": null,
          "min": null,
          "show": true
        },
        {
          "format": "short",
          "label": null,
          "logBase": 1,
          "max": null,
          "min": null,
          "show": true
        }
      ],
      "yaxis": {
        "align": false,
        "alignLevel": null
      }
    },
    {
      "aliasColors": {},
      "bars": false,
      "dashLength": 10,
      "dashes": false,
      "datasource": "Prometheus",
      "fill": 1,
      "gridPos": {
        "h": 7,
        "w": 6,
        "x": 6,
        "y": 28
      },
      "id": 24,
      "legend": {
        "avg": false,
        "current": false,
        "max": false,
        "min": false,
        "show": true,
        "total": false,
        "values": false
      },
      "lines": true,
      "linewidth": 1,
      "links": [],
      "nullPointMode": "null",
      "percentage": false,
      "pointradius": 5,
      "points": false,
      "renderer": "flot",
      "seriesOverrides": [],
      "spaceLength": 10,
      "stack": true,
      "steppedLine": false,
      "targets": [
        {
          "$$hashKey": "object:3635",
          "expr": "avg(mem_used{host=\"$host\"})",
          "format": "time_series",
          "interval": "",
          "intervalFactor": 2,
          "legendFormat": "Used",
          "metric": "mem_used",
          "refId": "A",
          "step": 4
        },
        {
          "$$hashKey": "object:3636",
          "expr": "avg(mem_cached{host=\"$ost\"})",
          "format": "time_series",
          "intervalFactor": 2,
          "legendFormat": "Cached",
          "metric": "mem_used",
          "refId": "B",
          "step": 4
        },
        {
          "$$hashKey": "object:3637",
          "expr": "avg(mem_buffered{host=\"$host\"})",
          "format": "time_series",
          "intervalFactor": 2,
          "legendFormat": "Buffered",
          "metric": "mem_used",
          "refId": "C",
          "step": 4
        },
        {
          "$$hashKey": "object:3638",
          "expr": "avg(mem_free{host=\"$host\"})",
          "format": "time_series",
          "interval": "",
          "intervalFactor": 2,
          "legendFormat": "Free",
          "metric": "mem_used",
          "refId": "D",
          "step": 4
        }
      ],
      "thresholds": [],
      "timeFrom": null,
      "timeShift": null,
      "title": "Memory",
      "tooltip": {
        "shared": true,
        "sort": 0,
        "value_type": "individual"
      },
      "type": "graph",
      "xaxis": {
        "buckets": null,
        "mode": "time",
        "name": null,
        "show": true,
        "values": []
      },
      "yaxes": [
        {
          "format": "bytes",
          "label": null,
          "logBase": 1,
          "max": null,
          "min": "0",
          "show": true
        },
        {
          "format": "short",
          "label": null,
          "logBase": 1,
          "max": null,
          "min": null,
          "show": true
        }
      ],
      "yaxis": {
        "align": false,
        "alignLevel": null
      }
    },
    {
      "aliasColors": {},
      "bars": false,
      "dashLength": 10,
      "dashes": false,
      "datasource": "Prometheus",
      "fill": 1,
      "gridPos": {
        "h": 7,
        "w": 6,
        "x": 12,
        "y": 28
      },
      "id": 28,
      "legend": {
        "avg": false,
        "current": false,
        "max": false,
        "min": false,
        "show": true,
        "total": false,
        "values": false
      },
      "lines": true,
      "linewidth": 1,
      "links": [],
      "nullPointMode": "null",
      "percentage": false,
      "pointradius": 5,
      "points": false,
      "renderer": "flot",
      "seriesOverrides": [],
      "spaceLength": 10,
      "stack": true,
      "steppedLine": false,
      "targets": [
        {
          "$$hashKey": "object:3929",
          "expr": "avg(swap_used{host=\"$host\"})",
          "format": "time_series",
          "interval": "",
          "intervalFactor": 2,
          "legendFormat": "Used",
          "metric": "swap_used",
          "refId": "A",
          "step": 4
        },
        {
          "$$hashKey": "object:3930",
          "expr": "avg(swap_free{host=\"$host\"})",
          "format": "time_series",
          "intervalFactor": 2,
          "legendFormat": "Free",
          "metric": "swap_used",
          "refId": "B",
          "step": 4
        }
      ],
      "thresholds": [],
      "timeFrom": null,
      "timeShift": null,
      "title": "Swap",
      "tooltip": {
        "shared": true,
        "sort": 0,
        "value_type": "individual"
      },
      "type": "graph",
      "xaxis": {
        "buckets": null,
        "mode": "time",
        "name": null,
        "show": true,
        "values": []
      },
      "yaxes": [
        {
          "format": "bytes",
          "label": "",
          "logBase": 1,
          "max": null,
          "min": "0",
          "show": true
        },
        {
          "format": "bytes",
          "label": null,
          "logBase": 1,
          "max": null,
          "min": null,
          "show": true
        }
      ],
      "yaxis": {
        "align": false,
        "alignLevel": null
      }
    },
    {
      "aliasColors": {},
      "bars": false,
      "dashLength": 10,
      "dashes": false,
      "datasource": "Prometheus",
      "fill": 1,
      "gridPos": {
        "h": 7,
        "w": 6,
        "x": 18,
        "y": 28
      },
      "height": "",
      "id": 26,
      "legend": {
        "alignAsTable": true,
        "avg": true,
        "current": false,
        "max": true,
        "min": false,
        "rightSide": false,
        "show": true,
        "total": false,
        "values": true
      },
      "lines": true,
      "linewidth": 1,
      "links": [],
      "nullPointMode": "null",
      "percentage": false,
      "pointradius": 5,
      "points": false,
      "renderer": "flot",
      "seriesOverrides": [],
      "spaceLength": 10,
      "stack": false,
      "steppedLine": false,
      "targets": [
        {
          "$$hashKey": "object:3841",
          "expr": "avg(rate(net_bytes_recv{host=\"$host\", interface=\"ethsrv\"}[5m])) * 8",
          "format": "time_series",
          "intervalFactor": 2,
          "legendFormat": "RX ",
          "metric": "net_bytes_",
          "refId": "A",
          "step": 4
        },
        {
          "$$hashKey": "object:3842",
          "expr": "avg(rate(net_bytes_sent{host=\"$host\", interface=\"ethsrv\"}[5m])) * 8",
          "format": "time_series",
          "intervalFactor": 2,
          "legendFormat": "TX",
          "metric": "net_bytes_",
          "refId": "B",
          "step": 4
        }
      ],
      "thresholds": [],
      "timeFrom": null,
      "timeShift": null,
      "title": "Network ethsrv (Backend)",
      "tooltip": {
        "shared": true,
        "sort": 0,
        "value_type": "individual"
      },
      "type": "graph",
      "xaxis": {
        "buckets": null,
        "mode": "time",
        "name": null,
        "show": true,
        "values": []
      },
      "yaxes": [
        {
          "format": "bps",
          "label": null,
          "logBase": 1,
          "max": null,
          "min": null,
          "show": true
        },
        {
          "format": "short",
          "label": null,
          "logBase": 1,
          "max": null,
          "min": null,
          "show": true
        }
      ],
      "yaxis": {
        "align": false,
        "alignLevel": null
      }
    }
  ],
  "refresh": false,
  "schemaVersion": 16,
  "style": "dark",
  "tags": [
    "postgres",
    "fcio"
  ],
  "templating": {
    "list": [
      {
        "allValue": null,
        "current": {},
        "datasource": "Prometheus",
        "hide": 0,
        "includeAll": false,
        "label": null,
        "multi": false,
        "name": "host",
        "options": [],
        "query": "label_values(postgresql_checkpoints_req,host)",
        "refresh": 1,
        "regex": "",
        "sort": 0,
        "tagValuesQuery": "",
        "tags": [],
        "tagsQuery": "",
        "type": "query",
        "useTags": false
      },
      {
        "allValue": ".*",
        "current": {},
        "datasource": "Prometheus",
        "hide": 0,
        "includeAll": true,
        "label": "db",
        "multi": false,
        "name": "db",
        "options": [],
        "query": "label_values(postgresql_tup_fetched{host=\"$host\",db!~\"template.*|postgres\"}, db)",
        "refresh": 1,
        "regex": "",
        "sort": 0,
        "tagValuesQuery": "",
        "tags": [],
        "tagsQuery": "",
        "type": "query",
        "useTags": false
      }
    ]
  },
  "time": {
    "from": "now-1h",
    "to": "now"
  },
  "timepicker": {
    "refresh_intervals": [
      "5s",
      "10s",
      "30s",
      "1m",
      "5m",
      "15m",
      "30m",
      "1h",
      "2h",
      "1d"
    ],
    "time_options": [
      "5m",
      "15m",
      "1h",
      "6h",
      "12h",
      "24h",
      "2d",
      "7d",
      "30d"
    ]
  },
  "timezone": "browser",
  "title": "PostgreSQL",
  "uid": "fciopostgresql",
  "version": 2
}
