{
  "annotations": {
    "list": [
      {
        "builtIn": 1,
        "datasource": "-- Grafana --",
        "enable": true,
        "hide": true,
        "iconColor": "rgba(0, 211, 255, 1)",
        "name": "Annotations & Alerts",
        "type": "dashboard"
      }
    ]
  },
  "description": "Performance metrics for Postgres",
  "editable": true,
  "gnetId": 455,
  "graphTooltip": 1,
  "hideControls": false,
  "id": 6,
  "uid": "fciopostgresql",
  "links": [],
  "refresh": false,
  "rows": [
    {
      "collapse": false,
      "height": "250px",
      "panels": [
        {
          "aliasColors": {},
          "bars": false,
          "dashLength": 10,
          "dashes": false,
          "datasource": "Prometheus",
          "editable": true,
          "error": false,
          "fill": 1,
          "grid": {},
          "id": 1,
          "legend": {
            "alignAsTable": true,
            "avg": true,
            "current": false,
            "max": true,
            "min": true,
            "rightSide": true,
            "show": true,
            "total": false,
            "values": true
          },
          "lines": true,
          "linewidth": 1,
          "links": [],
          "nullPointMode": "connected",
          "percentage": false,
          "pointradius": 5,
          "points": false,
          "renderer": "flot",
          "seriesOverrides": [],
          "spaceLength": 10,
          "span": 9,
          "stack": false,
          "steppedLine": false,
          "targets": [
            {
              "alias": "fetched",
              "dsType": "prometheus",
              "expr": "sum(irate(postgresql_tup_fetched{db=~\"$db\",host=\"$host\"}[5m]))",
              "groupBy": [
                {
                  "params": [
                    "$interval"
                  ],
                  "type": "time"
                },
                {
                  "params": [
                    "null"
                  ],
                  "type": "fill"
                }
              ],
              "intervalFactor": 2,
              "legendFormat": "fetched",
              "measurement": "postgresql",
              "policy": "default",
              "refId": "A",
              "resultFormat": "time_series",
              "select": [
                [
                  {
                    "params": [
                      "tup_fetched"
                    ],
                    "type": "field"
                  },
                  {
                    "params": [],
                    "type": "mean"
                  },
                  {
                    "params": [
                      "10s"
                    ],
                    "type": "non_negative_derivative"
                  }
                ]
              ],
              "step": 120,
              "tags": [
                {
                  "key": "host",
                  "operator": "=~",
                  "value": "/^$host$/"
                }
              ]
            },
            {
              "alias": "fetched",
              "dsType": "prometheus",
              "expr": "sum(irate(postgresql_tup_returned{db=~\"$db\",host=\"$host\"}[5m]))",
              "groupBy": [
                {
                  "params": [
                    "$interval"
                  ],
                  "type": "time"
                },
                {
                  "params": [
                    "null"
                  ],
                  "type": "fill"
                }
              ],
              "intervalFactor": 2,
              "legendFormat": "returned",
              "measurement": "postgresql",
              "policy": "default",
              "refId": "B",
              "resultFormat": "time_series",
              "select": [
                [
                  {
                    "params": [
                      "tup_fetched"
                    ],
                    "type": "field"
                  },
                  {
                    "params": [],
                    "type": "mean"
                  },
                  {
                    "params": [
                      "10s"
                    ],
                    "type": "non_negative_derivative"
                  }
                ]
              ],
              "step": 120,
              "tags": [
                {
                  "key": "host",
                  "operator": "=~",
                  "value": "/^$host$/"
                }
              ]
            },
            {
              "alias": "fetched",
              "dsType": "prometheus",
              "expr": "sum(irate(postgresql_tup_inserted{db=~\"$db\",host=\"$host\"}[5m]))",
              "groupBy": [
                {
                  "params": [
                    "$interval"
                  ],
                  "type": "time"
                },
                {
                  "params": [
                    "null"
                  ],
                  "type": "fill"
                }
              ],
              "intervalFactor": 2,
              "legendFormat": "inserted",
              "measurement": "postgresql",
              "policy": "default",
              "refId": "C",
              "resultFormat": "time_series",
              "select": [
                [
                  {
                    "params": [
                      "tup_fetched"
                    ],
                    "type": "field"
                  },
                  {
                    "params": [],
                    "type": "mean"
                  },
                  {
                    "params": [
                      "10s"
                    ],
                    "type": "non_negative_derivative"
                  }
                ]
              ],
              "step": 120,
              "tags": [
                {
                  "key": "host",
                  "operator": "=~",
                  "value": "/^$host$/"
                }
              ]
            },
            {
              "alias": "fetched",
              "dsType": "prometheus",
              "expr": "sum(irate(postgresql_tup_updated{db=~\"$db\",host=\"$host\"}[5m]))",
              "groupBy": [
                {
                  "params": [
                    "$interval"
                  ],
                  "type": "time"
                },
                {
                  "params": [
                    "null"
                  ],
                  "type": "fill"
                }
              ],
              "intervalFactor": 2,
              "legendFormat": "updated",
              "measurement": "postgresql",
              "policy": "default",
              "refId": "D",
              "resultFormat": "time_series",
              "select": [
                [
                  {
                    "params": [
                      "tup_fetched"
                    ],
                    "type": "field"
                  },
                  {
                    "params": [],
                    "type": "mean"
                  },
                  {
                    "params": [
                      "10s"
                    ],
                    "type": "non_negative_derivative"
                  }
                ]
              ],
              "step": 120,
              "tags": [
                {
                  "key": "host",
                  "operator": "=~",
                  "value": "/^$host$/"
                }
              ]
            },
            {
              "alias": "fetched",
              "dsType": "prometheus",
              "expr": "sum(irate(postgresql_tup_deleted{db=~\"$db\",host=\"$host\"}[5m]))",
              "groupBy": [
                {
                  "params": [
                    "$interval"
                  ],
                  "type": "time"
                },
                {
                  "params": [
                    "null"
                  ],
                  "type": "fill"
                }
              ],
              "intervalFactor": 2,
              "legendFormat": "deleted",
              "measurement": "postgresql",
              "policy": "default",
              "refId": "E",
              "resultFormat": "time_series",
              "select": [
                [
                  {
                    "params": [
                      "tup_fetched"
                    ],
                    "type": "field"
                  },
                  {
                    "params": [],
                    "type": "mean"
                  },
                  {
                    "params": [
                      "10s"
                    ],
                    "type": "non_negative_derivative"
                  }
                ]
              ],
              "step": 120,
              "tags": [
                {
                  "key": "host",
                  "operator": "=~",
                  "value": "/^$host$/"
                }
              ]
            }
          ],
          "thresholds": [],
          "timeFrom": null,
          "timeShift": null,
          "title": "Rows",
          "tooltip": {
            "msResolution": true,
            "shared": true,
            "sort": 0,
            "value_type": "cumulative"
          },
          "type": "graph",
          "xaxis": {
            "buckets": null,
            "mode": "time",
            "name": null,
            "show": true,
            "values": []
          },
          "yaxes": [
            {
              "format": "short",
              "label": null,
              "logBase": 1,
              "max": null,
              "min": null,
              "show": true
            },
            {
              "format": "short",
              "label": null,
              "logBase": 1,
              "max": null,
              "min": null,
              "show": true
            }
          ]
        },
        {
          "cacheTimeout": null,
          "colorBackground": false,
          "colorValue": false,
          "colors": [
            "rgba(245, 54, 54, 0.9)",
            "rgba(237, 129, 40, 0.89)",
            "rgba(50, 172, 45, 0.97)"
          ],
          "datasource": "Prometheus",
          "decimals": 0,
          "editable": true,
          "error": false,
          "format": "none",
          "gauge": {
            "maxValue": 100,
            "minValue": 0,
            "show": false,
            "thresholdLabels": false,
            "thresholdMarkers": true
          },
          "height": "250",
          "id": 11,
          "interval": null,
          "links": [],
          "mappingType": 1,
          "mappingTypes": [
            {
              "name": "value to text",
              "value": 1
            },
            {
              "name": "range to text",
              "value": 2
            }
          ],
          "maxDataPoints": 100,
          "nullPointMode": "connected",
          "nullText": null,
          "postfix": "",
          "postfixFontSize": "50%",
          "prefix": "",
          "prefixFontSize": "50%",
          "rangeMaps": [
            {
              "from": "null",
              "text": "N/A",
              "to": "null"
            }
          ],
          "span": 3,
          "sparkline": {
            "fillColor": "rgba(31, 118, 189, 0.18)",
            "full": true,
            "lineColor": "rgb(31, 120, 193)",
            "show": true
          },
          "tableColumn": "",
          "targets": [
            {
              "dsType": "prometheus",
              "expr": "sum(irate(postgresql_xact_commit{db=~\"$db\",host=\"$host\"}[5m])) + sum(irate(postgresql_xact_rollback{db=~\"$db\",host=\"$host\"}[5m]))",
              "format": "time_series",
              "groupBy": [
                {
                  "params": [
                    "$interval"
                  ],
                  "type": "time"
                },
                {
                  "params": [
                    "null"
                  ],
                  "type": "fill"
                }
              ],
              "intervalFactor": 2,
              "measurement": "postgresql",
              "metric": "postgresql_xact_commit",
              "policy": "default",
              "refId": "A",
              "resultFormat": "time_series",
              "select": [
                [
                  {
                    "params": [
                      "xact_commit"
                    ],
                    "type": "field"
                  },
                  {
                    "params": [],
                    "type": "mean"
                  },
                  {
                    "params": [
                      "10s"
                    ],
                    "type": "non_negative_derivative"
                  }
                ]
              ],
              "step": 1800,
              "tags": [
                {
                  "key": "host",
                  "operator": "=~",
                  "value": "/^$host$/"
                }
              ]
            }
          ],
          "thresholds": "",
          "title": "QPS",
          "transparent": true,
          "type": "singlestat",
          "valueFontSize": "80%",
          "valueMaps": [
            {
              "op": "=",
              "text": "N/A",
              "value": "null"
            }
          ],
          "valueName": "avg"
        }
      ],
      "repeat": null,
      "repeatIteration": null,
      "repeatRowId": null,
      "showTitle": false,
      "title": "Row",
      "titleSize": "h6"
    },
    {
      "collapse": false,
      "height": 250,
      "panels": [
        {
          "aliasColors": {},
          "bars": false,
          "dashLength": 10,
          "dashes": false,
          "datasource": "Prometheus",
          "decimals": 1,
          "editable": true,
          "error": false,
          "fill": 1,
          "grid": {},
          "height": "",
          "id": 2,
          "legend": {
            "alignAsTable": true,
            "avg": true,
            "current": false,
            "hideZero": false,
            "max": true,
            "min": true,
            "rightSide": true,
            "show": true,
            "total": false,
            "values": true
          },
          "lines": true,
          "linewidth": 1,
          "links": [],
          "nullPointMode": "connected",
          "percentage": false,
          "pointradius": 5,
          "points": false,
          "renderer": "flot",
          "seriesOverrides": [],
          "spaceLength": 10,
          "span": 9,
          "stack": false,
          "steppedLine": false,
          "targets": [
            {
              "alias": "Buffers Allocated",
              "dsType": "prometheus",
              "expr": "rate(postgresql_buffers_alloc{host=\"$host\"}[5m])",
              "groupBy": [
                {
                  "params": [
                    "$interval"
                  ],
                  "type": "time"
                },
                {
                  "params": [
                    "null"
                  ],
                  "type": "fill"
                }
              ],
              "intervalFactor": 2,
              "legendFormat": "alloc",
              "measurement": "postgresql",
              "metric": "postgresql_buffers_alloc",
              "policy": "default",
              "refId": "A",
              "resultFormat": "time_series",
              "select": [
                [
                  {
                    "params": [
                      "buffers_alloc"
                    ],
                    "type": "field"
                  },
                  {
                    "params": [],
                    "type": "mean"
                  },
                  {
                    "params": [],
                    "type": "difference"
                  }
                ]
              ],
              "step": 120,
              "tags": [
                {
                  "key": "host",
                  "operator": "=~",
                  "value": "/^$host$/"
                }
              ]
            },
            {
              "alias": "Buffers Allocated",
              "dsType": "prometheus",
              "expr": "rate(postgresql_buffers_backend_fsync{host='$host'}[5m])",
              "groupBy": [
                {
                  "params": [
                    "$interval"
                  ],
                  "type": "time"
                },
                {
                  "params": [
                    "null"
                  ],
                  "type": "fill"
                }
              ],
              "intervalFactor": 2,
              "legendFormat": "backend_fsync",
              "measurement": "postgresql",
              "metric": "postgresql_buffers_backend_fsync",
              "policy": "default",
              "refId": "B",
              "resultFormat": "time_series",
              "select": [
                [
                  {
                    "params": [
                      "buffers_alloc"
                    ],
                    "type": "field"
                  },
                  {
                    "params": [],
                    "type": "mean"
                  },
                  {
                    "params": [],
                    "type": "difference"
                  }
                ]
              ],
              "step": 120,
              "tags": [
                {
                  "key": "host",
                  "operator": "=~",
                  "value": "/^$host$/"
                }
              ]
            },
            {
              "alias": "Buffers Allocated",
              "dsType": "prometheus",
              "expr": "rate(postgresql_buffers_backend{host='$host'}[5m])",
              "groupBy": [
                {
                  "params": [
                    "$interval"
                  ],
                  "type": "time"
                },
                {
                  "params": [
                    "null"
                  ],
                  "type": "fill"
                }
              ],
              "intervalFactor": 2,
              "legendFormat": "backend",
              "measurement": "postgresql",
              "metric": "postgresql_buffers_backend",
              "policy": "default",
              "refId": "C",
              "resultFormat": "time_series",
              "select": [
                [
                  {
                    "params": [
                      "buffers_alloc"
                    ],
                    "type": "field"
                  },
                  {
                    "params": [],
                    "type": "mean"
                  },
                  {
                    "params": [],
                    "type": "difference"
                  }
                ]
              ],
              "step": 120,
              "tags": [
                {
                  "key": "host",
                  "operator": "=~",
                  "value": "/^$host$/"
                }
              ]
            },
            {
              "alias": "Buffers Allocated",
              "dsType": "prometheus",
              "expr": "rate(postgresql_buffers_clean{host='$host'}[5m])",
              "groupBy": [
                {
                  "params": [
                    "$interval"
                  ],
                  "type": "time"
                },
                {
                  "params": [
                    "null"
                  ],
                  "type": "fill"
                }
              ],
              "intervalFactor": 2,
              "legendFormat": "clean",
              "measurement": "postgresql",
              "metric": "postgresql_buffers_clean",
              "policy": "default",
              "refId": "D",
              "resultFormat": "time_series",
              "select": [
                [
                  {
                    "params": [
                      "buffers_alloc"
                    ],
                    "type": "field"
                  },
                  {
                    "params": [],
                    "type": "mean"
                  },
                  {
                    "params": [],
                    "type": "difference"
                  }
                ]
              ],
              "step": 120,
              "tags": [
                {
                  "key": "host",
                  "operator": "=~",
                  "value": "/^$host$/"
                }
              ]
            },
            {
              "alias": "Buffers Allocated",
              "dsType": "prometheus",
              "expr": "rate(postgresql_buffers_checkpoint{host='$host'}[5m])",
              "groupBy": [
                {
                  "params": [
                    "$interval"
                  ],
                  "type": "time"
                },
                {
                  "params": [
                    "null"
                  ],
                  "type": "fill"
                }
              ],
              "interval": "",
              "intervalFactor": 2,
              "legendFormat": "checkpoint",
              "measurement": "postgresql",
              "metric": "postgresql_buffers_checkpoint",
              "policy": "default",
              "refId": "E",
              "resultFormat": "time_series",
              "select": [
                [
                  {
                    "params": [
                      "buffers_alloc"
                    ],
                    "type": "field"
                  },
                  {
                    "params": [],
                    "type": "mean"
                  },
                  {
                    "params": [],
                    "type": "difference"
                  }
                ]
              ],
              "step": 120,
              "tags": [
                {
                  "key": "host",
                  "operator": "=~",
                  "value": "/^$host$/"
                }
              ]
            }
          ],
          "thresholds": [],
          "timeFrom": null,
          "timeShift": null,
          "title": "Buffers",
          "tooltip": {
            "msResolution": false,
            "shared": true,
            "sort": 0,
            "value_type": "cumulative"
          },
          "type": "graph",
          "xaxis": {
            "buckets": null,
            "mode": "time",
            "name": null,
            "show": true,
            "values": []
          },
          "yaxes": [
            {
              "format": "short",
              "label": null,
              "logBase": 1,
              "max": null,
              "min": 0,
              "show": true
            },
            {
              "format": "short",
              "label": null,
              "logBase": 1,
              "max": null,
              "min": null,
              "show": true
            }
          ]
        },
        {
          "cacheTimeout": null,
          "colorBackground": false,
          "colorValue": false,
          "colors": [
            "rgba(245, 54, 54, 0.9)",
            "rgba(237, 129, 40, 0.89)",
            "rgba(50, 172, 45, 0.97)"
          ],
          "datasource": "Prometheus",
          "decimals": 0,
          "editable": true,
          "error": false,
          "format": "none",
          "gauge": {
            "maxValue": 100,
            "minValue": 0,
            "show": false,
            "thresholdLabels": false,
            "thresholdMarkers": true
          },
          "height": "250",
          "id": 13,
          "interval": null,
          "links": [],
          "mappingType": 1,
          "mappingTypes": [
            {
              "name": "value to text",
              "value": 1
            },
            {
              "name": "range to text",
              "value": 2
            }
          ],
          "maxDataPoints": 100,
          "nullPointMode": "connected",
          "nullText": null,
          "postfix": "",
          "postfixFontSize": "50%",
          "prefix": "",
          "prefixFontSize": "50%",
          "rangeMaps": [
            {
              "from": "null",
              "text": "N/A",
              "to": "null"
            }
          ],
          "span": 3,
          "sparkline": {
            "fillColor": "rgba(31, 118, 189, 0.18)",
            "full": true,
            "lineColor": "rgb(31, 120, 193)",
            "show": true
          },
          "tableColumn": "",
          "targets": [
            {
              "dsType": "prometheus",
              "expr": "max(postgresql_numbackends{db=~\"$db\",host=\"$host\"})",
              "groupBy": [
                {
                  "params": [
                    "$interval"
                  ],
                  "type": "time"
                },
                {
                  "params": [
                    "null"
                  ],
                  "type": "fill"
                }
              ],
              "intervalFactor": 2,
              "measurement": "postgresql",
              "metric": "postgresql_xact_commit",
              "policy": "default",
              "refId": "A",
              "resultFormat": "time_series",
              "select": [
                [
                  {
                    "params": [
                      "xact_commit"
                    ],
                    "type": "field"
                  },
                  {
                    "params": [],
                    "type": "mean"
                  },
                  {
                    "params": [
                      "10s"
                    ],
                    "type": "non_negative_derivative"
                  }
                ]
              ],
              "step": 1800,
              "tags": [
                {
                  "key": "host",
                  "operator": "=~",
                  "value": "/^$host$/"
                }
              ]
            }
          ],
          "thresholds": "",
          "title": "Connections",
          "transparent": true,
          "type": "singlestat",
          "valueFontSize": "80%",
          "valueMaps": [
            {
              "op": "=",
              "text": "N/A",
              "value": "null"
            }
          ],
          "valueName": "current"
        }
      ],
      "repeat": null,
      "repeatIteration": null,
      "repeatRowId": null,
      "showTitle": false,
      "title": "Dashboard Row",
      "titleSize": "h6"
    },
    {
      "collapse": false,
      "height": "250px",
      "panels": [
        {
          "aliasColors": {},
          "bars": false,
          "dashLength": 10,
          "dashes": false,
          "datasource": "Prometheus",
          "editable": true,
          "error": false,
          "fill": 1,
          "grid": {},
          "id": 12,
          "legend": {
            "avg": false,
            "current": false,
            "max": false,
            "min": false,
            "show": true,
            "total": false,
            "values": false
          },
          "lines": true,
          "linewidth": 2,
          "links": [],
          "nullPointMode": "connected",
          "percentage": true,
          "pointradius": 1,
          "points": false,
          "renderer": "flot",
          "seriesOverrides": [],
          "spaceLength": 10,
          "span": 6,
          "stack": false,
          "steppedLine": false,
          "targets": [
            {
              "expr": "sum(postgresql_blks_hit{db=~\"$db\",host=\"$host\"}) / (sum(postgresql_blks_hit{db=~\"$db\",host=\"$host\"}) + sum(postgresql_blks_read{db=~\"$db\",host=\"$host\"}))",
              "intervalFactor": 2,
              "legendFormat": "cache hit rate",
              "metric": "postgresql_blks",
              "refId": "A",
              "step": 240
            },
            {
              "expr": "",
              "intervalFactor": 2,
              "metric": "postg",
              "refId": "B"
            }
          ],
          "thresholds": [],
          "timeFrom": null,
          "timeShift": null,
          "title": "Cache hit ratio",
          "tooltip": {
            "msResolution": false,
            "shared": true,
            "sort": 0,
            "value_type": "cumulative"
          },
          "type": "graph",
          "xaxis": {
            "buckets": null,
            "mode": "time",
            "name": null,
            "show": true,
            "values": []
          },
          "yaxes": [
            {
              "format": "percentunit",
              "label": "",
              "logBase": 1,
              "max": null,
              "min": "0",
              "show": true
            },
            {
              "format": "short",
              "label": null,
              "logBase": 1,
              "max": null,
              "min": null,
              "show": true
            }
          ]
        },
        {
          "aliasColors": {},
          "bars": false,
          "dashLength": 10,
          "dashes": false,
          "datasource": "Prometheus",
          "editable": true,
          "error": false,
          "fill": 1,
          "grid": {},
          "id": 3,
          "legend": {
            "avg": false,
            "current": false,
            "max": false,
            "min": false,
            "show": true,
            "total": false,
            "values": false
          },
          "lines": true,
          "linewidth": 2,
          "links": [],
          "nullPointMode": "connected",
          "percentage": false,
          "pointradius": 5,
          "points": false,
          "renderer": "flot",
          "seriesOverrides": [],
          "spaceLength": 10,
          "span": 6,
          "stack": false,
          "steppedLine": false,
          "targets": [
            {
              "alias": "conflicts",
              "dsType": "prometheus",
              "expr": "sum(rate(postgresql_deadlocks{db=~\"$db\",host=\"$host\"}[5m]))",
              "groupBy": [
                {
                  "params": [
                    "$interval"
                  ],
                  "type": "time"
                },
                {
                  "params": [
                    "null"
                  ],
                  "type": "fill"
                }
              ],
              "intervalFactor": 2,
              "legendFormat": "deadlocks",
              "measurement": "postgresql",
              "metric": "postgresql_deadlocks",
              "policy": "default",
              "refId": "A",
              "resultFormat": "time_series",
              "select": [
                [
                  {
                    "params": [
                      "conflicts"
                    ],
                    "type": "field"
                  },
                  {
                    "params": [],
                    "type": "mean"
                  },
                  {
                    "params": [],
                    "type": "difference"
                  }
                ]
              ],
              "step": 240,
              "tags": [
                {
                  "key": "host",
                  "operator": "=~",
                  "value": "/^$host$/"
                }
              ]
            },
            {
              "alias": "deadlocks",
              "dsType": "prometheus",
              "expr": "sum(rate(postgresql_conflicts{db=~\"$db\",host=\"$host\"}[5m]))",
              "groupBy": [
                {
                  "params": [
                    "$interval"
                  ],
                  "type": "time"
                },
                {
                  "params": [
                    "null"
                  ],
                  "type": "fill"
                }
              ],
              "intervalFactor": 2,
              "legendFormat": "conflicts",
              "measurement": "postgresql",
              "metric": "postgresql_conflicts",
              "policy": "default",
              "refId": "B",
              "resultFormat": "time_series",
              "select": [
                [
                  {
                    "params": [
                      "deadlocks"
                    ],
                    "type": "field"
                  },
                  {
                    "params": [],
                    "type": "mean"
                  },
                  {
                    "params": [],
                    "type": "difference"
                  }
                ]
              ],
              "step": 240,
              "tags": [
                {
                  "key": "host",
                  "operator": "=~",
                  "value": "/^$host$/"
                }
              ]
            }
          ],
          "thresholds": [],
          "timeFrom": null,
          "timeShift": null,
          "title": "Conflicts/Deadlocks",
          "tooltip": {
            "msResolution": false,
            "shared": true,
            "sort": 0,
            "value_type": "cumulative"
          },
          "type": "graph",
          "xaxis": {
            "buckets": null,
            "mode": "time",
            "name": null,
            "show": true,
            "values": []
          },
          "yaxes": [
            {
              "format": "short",
              "label": null,
              "logBase": 1,
              "max": null,
              "min": 0,
              "show": true
            },
            {
              "format": "short",
              "label": null,
              "logBase": 1,
              "max": null,
              "min": null,
              "show": true
            }
          ]
        }
      ],
      "repeat": null,
      "repeatIteration": null,
      "repeatRowId": null,
      "showTitle": false,
      "title": "New row",
      "titleSize": "h6"
    }
  ],
  "schemaVersion": 14,
  "style": "dark",
  "tags": [
    "postgres",
    "fcio"
  ],
  "templating": {
    "list": [
      {
        "allValue": null,
        "current": {
          "tags": [],
          "text": "bb3prod13",
          "value": "bb3prod13"
        },
        "datasource": "Prometheus",
        "hide": 0,
        "includeAll": false,
        "label": null,
        "multi": false,
        "name": "host",
        "options": [],
        "query": "label_values(postgresql_checkpoints_req,host)",
        "refresh": 1,
        "regex": "",
        "sort": 0,
        "tagValuesQuery": "",
        "tags": [],
        "tagsQuery": "",
        "type": "query",
        "useTags": false
      },
      {
        "allValue": ".*",
        "current": {
          "text": "All",
          "value": "$__all"
        },
        "datasource": "Prometheus",
        "hide": 0,
        "includeAll": true,
        "label": "db",
        "multi": false,
        "name": "db",
        "options": [],
        "query": "label_values(postgresql_tup_fetched{host=\"$host\",db!~\"template.*|postgres\"}, db)",
        "refresh": 1,
        "regex": "",
        "sort": 0,
        "tagValuesQuery": "",
        "tags": [],
        "tagsQuery": "",
        "type": "query",
        "useTags": false
      }
    ]
  },
  "time": {
    "from": "now-1h",
    "to": "now"
  },
  "timepicker": {
    "refresh_intervals": [
      "5s",
      "10s",
      "30s",
      "1m",
      "5m",
      "15m",
      "30m",
      "1h",
      "2h",
      "1d"
    ],
    "time_options": [
      "5m",
      "15m",
      "1h",
      "6h",
      "12h",
      "24h",
      "2d",
      "7d",
      "30d"
    ]
  },
  "timezone": "browser",
  "title": "PostgreSQL",
  "version": 7
}
